setup.py
calexicon/__init__.py
calexicon/constants.py
calexicon.egg-info/PKG-INFO
calexicon.egg-info/SOURCES.txt
calexicon.egg-info/dependency_links.txt
calexicon.egg-info/top_level.txt
calexicon/calendars/__init__.py
calexicon/calendars/base.py
calexicon/calendars/historical.py
calexicon/calendars/main.py
calexicon/calendars/other.py
calexicon/dates/__init__.py
calexicon/dates/base.py
calexicon/dates/bce.py
calexicon/dates/distant.py
calexicon/dates/overflow.py
calexicon/fn/__init__.py
calexicon/fn/iso.py
calexicon/fn/julian.py
calexicon/internal/__init__.py
calexicon/internal/exception.py
calexicon/internal/general.py
calexicon/internal/gregorian.py
calexicon/internal/julian.py
calexicon/internal/output.py