Metadata-Version: 1.0
Name: calexicon
Version: 0.1
Summary: Calendar stuff
Home-page: http://github.com/jwg4/calexicon
Author: Jack Grahl
Author-email: jack.grahl@yahoo.co.uk
License: Apache License 2.0
Platform: UNKNOWN
